publish/__init__.py
publish/algorithms.py
publish/common.py
publish/database.py
publish/exceptions.py
publish/exporting.py
publish/filtering.py
publish/importing.py
publish/interaction.py
publish/keygeneration.py
publish/log.py
publish/merging.py
publish/printing.py
publish/validation.py
publish/config/__init__.py
publish/config/defaults.py
publish/config/formatting.py
publish/formats/__init__.py
publish/formats/bibtex.py
publish/formats/graphml.py
publish/formats/html.py
publish/formats/latex.py
publish/formats/pdf.py
publish/formats/pub.py
publish/formats/rst.py
publish_doconce-1.1.4.data/data/share/man/man1/publish.1.gz
publish_doconce-1.1.4.data/scripts/publish
publish_doconce-1.1.4.dist-info/COPYING
publish_doconce-1.1.4.dist-info/LICENSE
publish_doconce-1.1.4.dist-info/METADATA
publish_doconce-1.1.4.dist-info/WHEEL
publish_doconce-1.1.4.dist-info/top_level.txt
publish_doconce-1.1.4.dist-info/RECORD
