Metadata-Version: 2.1
Name: publish-doconce
Version: 1.1.4
Summary: Distributed publication management system
Home-page: https://github.com/doconce/publish
Author: Logg Systems/Anna Logg
Author-email: anna@loggsystems.se
Maintainer: Alessandro Marin
Maintainer-email: alessandro.marin@fys.uio.no
License: UNKNOWN
Platform: UNKNOWN
Classifier: Development Status :: 5 - Production/Stable
Classifier: Intended Audience :: Science/Research
Classifier: License :: OSI Approved :: GNU General Public License v3 or later (GPLv3+)
Classifier: Environment :: Console
Classifier: Programming Language :: Python :: 3
Requires-Python: >=3.6
